pytest_tcpclient/__init__.py
pytest_tcpclient/framing.py
pytest_tcpclient/plugin.py
pytest_tcpclient-0.7.29.dist-info/LICENSE
pytest_tcpclient-0.7.29.dist-info/METADATA
pytest_tcpclient-0.7.29.dist-info/WHEEL
pytest_tcpclient-0.7.29.dist-info/entry_points.txt
pytest_tcpclient-0.7.29.dist-info/top_level.txt
pytest_tcpclient-0.7.29.dist-info/RECORD
