Metadata-Version: 2.1
Name: pytest-tcpclient
Version: 0.7.29
Summary: A pytest plugin for testing TCP clients
Author-email: Anders Lindstrom <anders@anderslindstrom.com>
Project-URL: Homepage, https://github.com/andersglindstrom/pytest-tcpclient.git
Classifier: Programming Language :: Python :: 3
Classifier: License :: OSI Approved :: MIT License
Classifier: Operating System :: OS Independent
Requires-Python: >=3.8
License-File: LICENSE
Requires-Dist: pytest (<8,>=7.1.3)
Requires-Dist: pytest-asyncio
Requires-Dist: pytest-mock
Provides-Extra: dev
Requires-Dist: build (>=0.8.0) ; extra == 'dev'
Requires-Dist: coverage (<6,>=5.3.1) ; extra == 'dev'
Requires-Dist: pycodestyle (<3,>=2.5.0) ; extra == 'dev'
Requires-Dist: pytest-cov (<5,>=4.0.0) ; extra == 'dev'
Requires-Dist: rst-include (~=2.1) ; extra == 'dev'
Requires-Dist: tox (<4,>=3.14.6) ; extra == 'dev'
Requires-Dist: twine (>=3.1.1) ; extra == 'dev'
